MANIFEST.in
README.txt
setup.cfg
setup.py
docs/HISTORY.txt
docs/INSTALL.txt
docs/LICENSE.GPL
docs/LICENSE.txt
enpraxis/__init__.py
enpraxis.staticsite.egg-info/PKG-INFO
enpraxis.staticsite.egg-info/SOURCES.txt
enpraxis.staticsite.egg-info/dependency_links.txt
enpraxis.staticsite.egg-info/entry_points.txt
enpraxis.staticsite.egg-info/namespace_packages.txt
enpraxis.staticsite.egg-info/not-zip-safe
enpraxis.staticsite.egg-info/paster_plugins.txt
enpraxis.staticsite.egg-info/requires.txt
enpraxis.staticsite.egg-info/top_level.txt
enpraxis/staticsite/__init__.py
enpraxis/staticsite/configure.zcml
enpraxis/staticsite/version.txt
enpraxis/staticsite/browser/__init__.py
enpraxis/staticsite/browser/configure.zcml
enpraxis/staticsite/browser/controlpanel.py
enpraxis/staticsite/browser/deployed.pt
enpraxis/staticsite/browser/deployform.py
enpraxis/staticsite/browser/static_site.png
enpraxis/staticsite/docs/README.html
enpraxis/staticsite/docs/web.css
enpraxis/staticsite/docs/images/base1.png
enpraxis/staticsite/docs/images/base2.png
enpraxis/staticsite/docs/images/css.png
enpraxis/staticsite/docs/images/deploy.png
enpraxis/staticsite/docs/images/deploy2.png
enpraxis/staticsite/docs/images/deployment.png
enpraxis/staticsite/docs/images/ignored.png
enpraxis/staticsite/docs/images/portlets.png
enpraxis/staticsite/docs/images/site_setup.png
enpraxis/staticsite/docs/images/states.png
enpraxis/staticsite/docs/images/views.png
enpraxis/staticsite/docs/src/README.rst
enpraxis/staticsite/i18n/plone-af.po
enpraxis/staticsite/i18n/plone-ar.po
enpraxis/staticsite/i18n/plone-bn.po
enpraxis/staticsite/i18n/plone-ca.po
enpraxis/staticsite/i18n/plone-de.po
enpraxis/staticsite/i18n/plone-en.po
enpraxis/staticsite/i18n/plone-es.po
enpraxis/staticsite/i18n/plone-fr.po
enpraxis/staticsite/i18n/plone-hi.po
enpraxis/staticsite/i18n/plone-hu.po
enpraxis/staticsite/i18n/plone-it.po
enpraxis/staticsite/i18n/plone-ja.po
enpraxis/staticsite/i18n/plone-ko.po
enpraxis/staticsite/i18n/plone-ne.po
enpraxis/staticsite/i18n/plone-nl.po
enpraxis/staticsite/i18n/plone-pt-br.po
enpraxis/staticsite/i18n/plone-pt.po
enpraxis/staticsite/i18n/plone-ru.po
enpraxis/staticsite/i18n/plone-tr.po
enpraxis/staticsite/i18n/plone-vi.po
enpraxis/staticsite/i18n/plone-zh-cn.po
enpraxis/staticsite/i18n/plone-zh-hk.po
enpraxis/staticsite/i18n/plone-zh-tw.po
enpraxis/staticsite/i18n/plone-zh.po
