Metadata-Version: 1.0
Name: enpraxis.staticsite
Version: 2.2
Summary: Create a static web site from your plone instance.
Home-page: http://svn.plone.org/svn/plone/plone.example
Author: enPraxis
Author-email: developer@enpraxis.net
License: GPL
Platform: UNKNOWN
Classifier: Framework :: Plone
Classifier: Programming Language :: Python
Classifier: Topic :: Software Development :: Libraries :: Python Modules
